Metadata-Version: 2.1
Name: Processador-de-Imagens
Version: 0.0.1
Summary: Pacote de processamento de imagem usando Skimage
Home-page: https://github.com/leoalvessantana/BootCamp-Dio-Geracao-Tech-Unimed-BH-ciencia-de-dados/tree/main/1.Python%20para%20Cientista%20de%20Dados
Author: Leonardo Santana
Author-email: leonardoalvs12@gmail.com
Requires-Python: >=3.8
Requires-Dist: matplotlib
Requires-Dist: numpy
Requires-Dist: scikit-image (>=0.16.1)
